reentry/__init__.py
reentry/abcbackend.py
reentry/cli.py
reentry/config.py
reentry/default_manager.py
reentry/entrypoint.py
reentry/hooks.py
reentry/js_data
reentry/jsonbackend.py
reentry/tests/test_data.json
reentry-1.3.3.dist-info/LICENSE
reentry-1.3.3.dist-info/METADATA
reentry-1.3.3.dist-info/WHEEL
reentry-1.3.3.dist-info/entry_points.txt
reentry-1.3.3.dist-info/top_level.txt
reentry-1.3.3.dist-info/RECORD
