Metadata-Version: 2.1
Name: reentry
Version: 1.3.3
Summary: A plugin manager based on setuptools entry points mechanism
Home-page: https://github.com/dropd/reentry
Author: Rico Haeuselmann
License: MIT License
Platform: UNKNOWN
Classifier: License :: OSI Approved :: MIT License
Classifier: Programming Language :: Python :: 2
Classifier: Programming Language :: Python :: 3
Classifier: Development Status :: 5 - Production/Stable
Classifier: Environment :: Plugins
Classifier: Intended Audience :: Developers
Classifier: Topic :: Software Development
Requires-Dist: setuptools (>=36.2)
Requires-Dist: click
Requires-Dist: six
Requires-Dist: pathlib2 ; python_version < "3.5"
Provides-Extra: pre-commit
Requires-Dist: pre-commit (~=2.2) ; extra == 'pre-commit'
Requires-Dist: pylint (~=2.6.0) ; extra == 'pre-commit'
Requires-Dist: flake8 ; extra == 'pre-commit'
Requires-Dist: tox ; extra == 'pre-commit'
Requires-Dist: packaging ; extra == 'pre-commit'
Provides-Extra: tests
Requires-Dist: pytest ; extra == 'tests'
Requires-Dist: coverage ; extra == 'tests'
Requires-Dist: pytest-cov ; extra == 'tests'
Requires-Dist: wheel ; extra == 'tests'
Requires-Dist: tox ; extra == 'tests'
